SimpleBinderGTA5Package/__init__.py
SimpleBinderGTA5Package/binds.py
SimpleBinderGTA5Package-2.dist-info/METADATA
SimpleBinderGTA5Package-2.dist-info/WHEEL
SimpleBinderGTA5Package-2.dist-info/top_level.txt
SimpleBinderGTA5Package-2.dist-info/RECORD
